tap_sls/__init__.py
tap_sls/client.py
tap_sls/schemas/directory.json
tap_sls/streams.py
tap_sls/tap.py
tap_sls/tests/__init__.py
tap_sls/tests/c1.py
tap_sls/tests/p1.py
tap_sls/tests/test_core.py
tap_sls-0.0.2.dist-info/entry_points.txt
tap_sls-0.0.2.dist-info/WHEEL
tap_sls-0.0.2.dist-info/METADATA
tap_sls-0.0.2.dist-info/RECORD
